Metadata-Version: 2.1
Name: ingreInsight3
Version: 0.1.0
Summary: A library for the Ingredient Insight app
Author: Hunter White
